openexr_tools/__init__.py
openexr_tools/enum.py
openexr_tools/py.typed
openexr_tools/tools.py
openexr_tools-0.5.0.dist-info/WHEEL
openexr_tools-0.5.0.dist-info/METADATA
openexr_tools-0.5.0.dist-info/licenses/LICENSE
openexr_tools-0.5.0.dist-info/RECORD
