Metadata-Version: 2.1
Name: openexr-tools
Version: 0.5.0
Summary: Tools for working with OpenEXR image files.
License: MIT
Keywords: OpenEXR,EXR,VFX,openexr,exr,vfx,computer-vision,cv,image,compositing
Author-email: Alex Braun <alexander.g.braun@gmail.com>
Requires-Python: >=3.10
Classifier: Development Status :: 4 - Beta
Classifier: Intended Audience :: Developers
Classifier: License :: OSI Approved :: MIT License
Classifier: Programming Language :: Python :: 3
Classifier: Programming Language :: Python :: 3.10
Classifier: Programming Language :: Python :: 3.11
Classifier: Programming Language :: Python :: 3.12
Classifier: Programming Language :: Python :: 3.13
Classifier: Typing :: Typed
Requires-Dist: lunchbox>=0.3.3
Requires-Dist: numpy
Requires-Dist: openexr-python>=2024.1.5.11.15.26
Project-URL: documentation, https://theNewFlesh.github.io/openexr-tools
Project-URL: repository, https://github.com/thenewflesh/openexr-tools
